dimod_cache.py
dimod_cache-0.0.0.dist-info/METADATA
dimod_cache-0.0.0.dist-info/WHEEL
dimod_cache-0.0.0.dist-info/top_level.txt
dimod_cache-0.0.0.dist-info/RECORD
