Metadata-Version: 2.1
Name: dimod-cache
Version: 0.0.0
Summary: A replay cache for the `dimod.Sampler`-class.
Author-email: Janus <janus@insignificancegalore.net>
License: MIT License
Keywords: dimod,cache
Classifier: Programming Language :: Python :: 3
Requires-Python: >=3.8
Requires-Dist: dimod
Requires-Dist: numpy
